depthai.cpython-37m-aarch64-linux-gnu.so
libdepthai-core.so
depthai_cli/__init__.py
depthai_cli/depthai_cli.py
depthai_cli/stress_test.py
depthai_cli/cam_test.py
depthai_cli/cam_test_gui.py
depthai-3.1.0.dist-info/entry_points.txt
depthai-3.1.0.dist-info/METADATA
depthai-3.1.0.dist-info/RECORD
depthai-3.1.0.dist-info/LICENSE
depthai-3.1.0.dist-info/WHEEL
depthai-3.1.0.dist-info/top_level.txt
depthai/modelzoo.pyi
depthai/py.typed
depthai/__init__.pyi
depthai/node/internal.pyi
depthai/node/__init__.pyi
depthai/nn_archive/__init__.pyi
depthai/nn_archive/v1.pyi
depthai/filters/params.pyi
depthai/filters/__init__.pyi
depthai.libs/libdepthai-core-d07f6184.so
depthai.libs/libavfilter-5cb5f458.so.10.4.100
depthai.libs/libavdevice-4574226a.so.61.3.100
depthai.libs/libavcodec-e84aaf3f.so.61.19.101
depthai.libs/libswscale-5d4b68b1.so.8.3.100
depthai.libs/libavutil-4b79800f.so.59.39.100
depthai.libs/libgomp-98df74fd.so.1.0.0
depthai.libs/libswresample-51740637.so.5.3.100
depthai.libs/libdynamic_calibration-eece70bd.so
depthai.libs/libavformat-527473c1.so.61.7.100
depthai.libs/libusb-1-6895b894.0.so
